preshed/__init__.pxd
preshed/__init__.py
preshed/about.py
preshed/bloom.cp38-win_amd64.pyd
preshed/bloom.pxd
preshed/bloom.pyx
preshed/counter.cp38-win_amd64.pyd
preshed/counter.pxd
preshed/counter.pyx
preshed/maps.cp38-win_amd64.pyd
preshed/maps.pxd
preshed/maps.pyx
preshed/tests/__init__.py
preshed/tests/test_bloom.py
preshed/tests/test_counter.py
preshed/tests/test_hashing.py
preshed/tests/test_pop.py
preshed-4.0.0.dist-info/LICENSE
preshed-4.0.0.dist-info/METADATA
preshed-4.0.0.dist-info/WHEEL
preshed-4.0.0.dist-info/top_level.txt
preshed-4.0.0.dist-info/RECORD
