Metadata-Version: 2.1
Name: preshed
Version: 4.0.0
Summary: Cython hash table that trusts the keys are pre-hashed
Home-page: https://github.com/explosion/preshed
Author: Explosion
Author-email: contact@explosion.ai
License: MIT
Classifier: Environment :: Console
Classifier: Intended Audience :: Developers
Classifier: Intended Audience :: Science/Research
Classifier: License :: OSI Approved :: MIT License
Classifier: Operating System :: POSIX :: Linux
Classifier: Operating System :: MacOS :: MacOS X
Classifier: Operating System :: Microsoft :: Windows
Classifier: Programming Language :: Cython
Classifier: Programming Language :: Python :: 3.6
Classifier: Programming Language :: Python :: 3.7
Classifier: Programming Language :: Python :: 3.8
Classifier: Programming Language :: Python :: 3.9
Classifier: Programming Language :: Python :: 3.10
Classifier: Programming Language :: Python :: 3.11
Classifier: Topic :: Scientific/Engineering
Requires-Python: >=3.6
License-File: LICENSE
Requires-Dist: cymem (<2.1.0,>=2.0.2)
Requires-Dist: murmurhash (<1.1.0,>=0.28.0)
